jmespath_community_fs/__init__.py
jmespath_community_fs/ast.py
jmespath_community_fs/compat.py
jmespath_community_fs/exceptions.py
jmespath_community_fs/functions.py
jmespath_community_fs/lexer.py
jmespath_community_fs/parser.py
jmespath_community_fs/scope.py
jmespath_community_fs/visitor.py
jmespath_community_fs-0.1.0.dist-info/LICENSE
jmespath_community_fs-0.1.0.dist-info/METADATA
jmespath_community_fs-0.1.0.dist-info/WHEEL
jmespath_community_fs-0.1.0.dist-info/RECORD
